elementarymaths/__init__.py
elementarymaths/add.py
elementarymaths/subtract.py
elementarymaths/extras/__init__.py
elementarymaths/extras/divide.py
elementarymaths/extras/multiply.py
elementarymaths-0.0.1.dist-info/METADATA
elementarymaths-0.0.1.dist-info/WHEEL
elementarymaths-0.0.1.dist-info/top_level.txt
elementarymaths-0.0.1.dist-info/RECORD
